astrojobs.py
astrojobs-0.0.5.dist-info/LICENSE
astrojobs-0.0.5.dist-info/METADATA
astrojobs-0.0.5.dist-info/WHEEL
astrojobs-0.0.5.dist-info/entry_points.txt
astrojobs-0.0.5.dist-info/top_level.txt
astrojobs-0.0.5.dist-info/RECORD
