Metadata-Version: 2.1
Name: astrojobs
Version: 0.0.5
Summary: Get the latest astronomy job and rumor news in your command line.
Home-page: https://github.com/pmocz/astrojobs
Author: Philip Mocz
Author-email: philip.mocz@gmail.com
Maintainer: Philip Mocz
Maintainer-email: philip.mocz@gmail.com
License: MIT
Download-URL: https://github.com/pmocz/astrojobs/archive/v0.0.5.tar.gz
Keywords: astronomy job rumor
Platform: UNKNOWN
Classifier: Environment :: Console
Classifier: Intended Audience :: End Users/Desktop
Classifier: Intended Audience :: Science/Research
Classifier: License :: OSI Approved :: MIT License
Classifier: Programming Language :: Python :: 2.7
Classifier: Programming Language :: Python :: 3.6
Classifier: Topic :: Scientific/Engineering :: Astronomy
License-File: LICENSE
Requires-Dist: bs4 (>=0.0.1)
Requires-Dist: urllib3 (>=1.25.7)
Requires-Dist: requests (>=2.0)
Requires-Dist: wasabi (>=0.8.2)
Requires-Dist: future (>=0.12.0) ; python_version < "3.0"
